glovo_data_platform_declarative_api/__init__.py
glovo_data_platform_declarative_api-0.0.0.dist-info/METADATA
glovo_data_platform_declarative_api-0.0.0.dist-info/WHEEL
glovo_data_platform_declarative_api-0.0.0.dist-info/top_level.txt
glovo_data_platform_declarative_api-0.0.0.dist-info/RECORD
